setup.cfg
setup.py
disembl/__init__.py
disembl/disembl.py
disembl/libdisembl.c
disembl.egg-info/PKG-INFO
disembl.egg-info/SOURCES.txt
disembl.egg-info/dependency_links.txt
disembl.egg-info/top_level.txt
disembl/scripts/DisEMBL.py
test/test_regression.py