Metadata-Version: 1.1
Name: disembl
Version: 2.0rc0
Summary: A refactoring/reimplementation of DisEMBL
Home-page: https://github.com/smsaladi/disembl
Author: Shyam Saladi
Author-email: saladi@caltech.edu
License: GNU General Public License v2 (GPLv2)
Download-URL: https://github.com/smsaladi/disembl/tarball/2.0
Keywords: protein,disorder,sequence,bioinformatics
Platform: UNKNOWN
